retracesoftware/__init__.py
retracesoftware/__main__.py
retracesoftware/autoenable.py
retracesoftware/config.json
retracesoftware/config.yaml
retracesoftware/exceptions.py
retracesoftware/modules.toml
retracesoftware/preload.txt
retracesoftware/replay.py
retracesoftware/retrace.pth
retracesoftware/run.py
retracesoftware/stackdifference.py
retracesoftware/install/__init__.py
retracesoftware/install/config.py
retracesoftware/install/edgecases.py
retracesoftware/install/globals.py
retracesoftware/install/install.py
retracesoftware/install/modulepatcher.py
retracesoftware/install/patcher.py
retracesoftware/install/patchfindspec.py
retracesoftware/install/phases.py
retracesoftware/install/predicate.py
retracesoftware/install/record.py
retracesoftware/install/references.py
retracesoftware/install/replace.py
retracesoftware/install/replay.py
retracesoftware/install/tracer.py
retracesoftware/install/typeutils.py
retracesoftware/proxy/__init__.py
retracesoftware/proxy/gateway.py
retracesoftware/proxy/globalref.py
retracesoftware/proxy/messagestream.py
retracesoftware/proxy/proxyfactory.py
retracesoftware/proxy/proxysystem.py
retracesoftware/proxy/proxytype.py
retracesoftware/proxy/record.py
retracesoftware/proxy/replay.py
retracesoftware/proxy/serializer.py
retracesoftware/proxy/startthread.py
retracesoftware/proxy/stubfactory.py
retracesoftware/proxy/thread.py
retracesoftware_proxy-0.2.17.dist-info/METADATA
retracesoftware_proxy-0.2.17.dist-info/WHEEL
retracesoftware_proxy-0.2.17.dist-info/top_level.txt
retracesoftware_proxy-0.2.17.dist-info/RECORD
