Metadata-Version: 2.4
Name: retracesoftware_proxy
Version: 0.2.17
License: Apache-2.0
Requires-Python: >=3.11
Requires-Dist: retracesoftware_utils
Requires-Dist: retracesoftware_functional
Requires-Dist: retracesoftware_stream
